<?xml version="1.0" ?>
<bpmn:definitions xmlns:bpmn="http://www.omg.org/spec/BPMN/20100524/MODEL" xmlns:bpmndi="http://www.omg.org/spec/BPMN/20100524/DI" xmlns:dc="http://www.omg.org/spec/DD/20100524/DC" xmlns:di="http://www.omg.org/spec/DD/20100524/DI" xmlns:ns1="http://bpmn-builder/metadata" id="Definitions_Activate_New_Mobility_Customer" targetNamespace="http://bpmn.io/schema/bpmn">
  <bpmn:process id="Process_Activate_New_Mobility_Customer" isExecutable="false">
    <bpmn:extensionElements>
      <ns1:journeyMetadata>
        <ns1:domainSequences>
          <ns1:sequence>2</ns1:sequence>
        </ns1:domainSequences>
        <ns1:subdomainSequences>
          <ns1:sequence>3</ns1:sequence>
        </ns1:subdomainSequences>
        <ns1:businessFlowSequences>
          <ns1:sequence>6</ns1:sequence>
        </ns1:businessFlowSequences>
        <ns1:applications>
          <ns1:application>
            <ns1:name>Avertack</ns1:name>
            <ns1:correlationIds>
              <ns1:id>25114</ns1:id>
            </ns1:correlationIds>
          </ns1:application>
          <ns1:application>
            <ns1:name>CAPM</ns1:name>
            <ns1:correlationIds>
              <ns1:id>73</ns1:id>
            </ns1:correlationIds>
          </ns1:application>
          <ns1:application>
            <ns1:name>CAS</ns1:name>
            <ns1:correlationIds>
              <ns1:id>18224</ns1:id>
            </ns1:correlationIds>
          </ns1:application>
          <ns1:application>
            <ns1:name>CPC</ns1:name>
            <ns1:correlationIds>
              <ns1:id>17765</ns1:id>
            </ns1:correlationIds>
          </ns1:application>
          <ns1:application>
            <ns1:name>CPOP</ns1:name>
            <ns1:correlationIds>
              <ns1:id>29607</ns1:id>
            </ns1:correlationIds>
          </ns1:application>
          <ns1:application>
            <ns1:name>CSI CPSVC</ns1:name>
            <ns1:correlationIds>
              <ns1:id>23901</ns1:id>
            </ns1:correlationIds>
          </ns1:application>
          <ns1:application>
            <ns1:name>CSI Customer Care</ns1:name>
            <ns1:correlationIds>
              <ns1:id>20182</ns1:id>
            </ns1:correlationIds>
          </ns1:application>
          <ns1:application>
            <ns1:name>CSI Parent Triage</ns1:name>
            <ns1:correlationIds>
              <ns1:id>17690</ns1:id>
            </ns1:correlationIds>
          </ns1:application>
          <ns1:application>
            <ns1:name>Digital IDP</ns1:name>
            <ns1:correlationIds>
              <ns1:id>27531</ns1:id>
            </ns1:correlationIds>
          </ns1:application>
          <ns1:application>
            <ns1:name>EDP</ns1:name>
            <ns1:correlationIds>
              <ns1:id>18211</ns1:id>
            </ns1:correlationIds>
          </ns1:application>
          <ns1:application>
            <ns1:name>Enabler C</ns1:name>
            <ns1:correlationIds>
              <ns1:id>18263</ns1:id>
            </ns1:correlationIds>
          </ns1:application>
          <ns1:application>
            <ns1:name>FED COMS</ns1:name>
            <ns1:correlationIds>
              <ns1:id>23283</ns1:id>
            </ns1:correlationIds>
          </ns1:application>
          <ns1:application>
            <ns1:name>FED US</ns1:name>
            <ns1:correlationIds>
              <ns1:id>24433</ns1:id>
            </ns1:correlationIds>
          </ns1:application>
          <ns1:application>
            <ns1:name>FED iCAS</ns1:name>
            <ns1:correlationIds>
              <ns1:id>23439</ns1:id>
            </ns1:correlationIds>
          </ns1:application>
          <ns1:application>
            <ns1:name>IDP Customer Graph Cloud</ns1:name>
            <ns1:correlationIds>
              <ns1:id>31468</ns1:id>
            </ns1:correlationIds>
          </ns1:application>
          <ns1:application>
            <ns1:name>INLAP</ns1:name>
            <ns1:correlationIds>
              <ns1:id>31374</ns1:id>
            </ns1:correlationIds>
          </ns1:application>
          <ns1:application>
            <ns1:name>NNA</ns1:name>
            <ns1:correlationIds>
              <ns1:id>17803</ns1:id>
            </ns1:correlationIds>
          </ns1:application>
          <ns1:application>
            <ns1:name>OPUS C</ns1:name>
            <ns1:correlationIds>
              <ns1:id>18257</ns1:id>
            </ns1:correlationIds>
          </ns1:application>
          <ns1:application>
            <ns1:name>ORACLE SCM</ns1:name>
            <ns1:correlationIds>
              <ns1:id>18249</ns1:id>
            </ns1:correlationIds>
          </ns1:application>
          <ns1:application>
            <ns1:name>Optical</ns1:name>
            <ns1:correlationIds>
              <ns1:id>17595</ns1:id>
            </ns1:correlationIds>
          </ns1:application>
          <ns1:application>
            <ns1:name>SC Switch Control TSC</ns1:name>
            <ns1:correlationIds>
              <ns1:id>18198</ns1:id>
            </ns1:correlationIds>
          </ns1:application>
          <ns1:application>
            <ns1:name>T Data</ns1:name>
            <ns1:correlationIds>
              <ns1:id>21948</ns1:id>
            </ns1:correlationIds>
          </ns1:application>
          <ns1:application>
            <ns1:name>TLG MOB</ns1:name>
            <ns1:correlationIds>
              <ns1:id>18193</ns1:id>
            </ns1:correlationIds>
          </ns1:application>
          <ns1:application>
            <ns1:name>UPM Prime Biller</ns1:name>
            <ns1:correlationIds>
              <ns1:id>29675</ns1:id>
            </ns1:correlationIds>
          </ns1:application>
          <ns1:application>
            <ns1:name>YODA</ns1:name>
            <ns1:correlationIds>
              <ns1:id>21053</ns1:id>
            </ns1:correlationIds>
          </ns1:application>
        </ns1:applications>
      </ns1:journeyMetadata>
    </bpmn:extensionElements>
    <bpmn:laneSet>
      <bpmn:lane id="Lane_1">
        <bpmn:flowNodeRef>StartEvent_1</bpmn:flowNodeRef>
        <bpmn:flowNodeRef>Task_Create_Account</bpmn:flowNodeRef>
        <bpmn:flowNodeRef>Task_Check_Credit</bpmn:flowNodeRef>
        <bpmn:flowNodeRef>Task_Configure_Account</bpmn:flowNodeRef>
        <bpmn:flowNodeRef>Task_Reserve_CTN</bpmn:flowNodeRef>
        <bpmn:flowNodeRef>Task_Review_Credit_Policy</bpmn:flowNodeRef>
        <bpmn:flowNodeRef>Task_Setup_Billing</bpmn:flowNodeRef>
        <bpmn:flowNodeRef>Task_Capture_TCP</bpmn:flowNodeRef>
        <bpmn:flowNodeRef>Task_Check_for_Fraud</bpmn:flowNodeRef>
        <bpmn:flowNodeRef>Task_Setup_Payment</bpmn:flowNodeRef>
        <bpmn:flowNodeRef>Task_Submit_Order</bpmn:flowNodeRef>
        <bpmn:flowNodeRef>EndEvent_1</bpmn:flowNodeRef>
      </bpmn:lane>
    </bpmn:laneSet>
    <bpmn:textAnnotation id="TextAnnotation_DiagramTitle">
      <bpmn:text>Line of Business: Mass Markets | Channel: Retail | Domain: Onboard  Activate | Subdomain: Setup  Activate | Product: Mobility | Business Flow: Activate New Mobility Customer</bpmn:text>
    </bpmn:textAnnotation>
    <bpmn:textAnnotation id="TextAnnotation_LastUpdated">
      <bpmn:text>Last Updated: 02/27/2026</bpmn:text>
    </bpmn:textAnnotation>
    <bpmn:startEvent id="StartEvent_1" name="Start"/>
    <bpmn:task id="Task_Create_Account" name="Create Account"/>
    <bpmn:task id="Task_Check_Credit" name="Check Credit"/>
    <bpmn:task id="Task_Configure_Account" name="Configure Account"/>
    <bpmn:task id="Task_Reserve_CTN" name="Reserve CTN"/>
    <bpmn:task id="Task_Review_Credit_Policy" name="Review Credit Policy"/>
    <bpmn:task id="Task_Setup_Billing" name="Setup Billing"/>
    <bpmn:task id="Task_Capture_TCP" name="Capture TCP"/>
    <bpmn:task id="Task_Check_for_Fraud" name="Check for Fraud"/>
    <bpmn:task id="Task_Setup_Payment" name="Setup Payment"/>
    <bpmn:task id="Task_Submit_Order" name="Submit Order"/>
    <bpmn:endEvent id="EndEvent_1" name="End"/>
    <bpmn:sequenceFlow id="Flow_1" sourceRef="StartEvent_1" targetRef="Task_Create_Account"/>
    <bpmn:sequenceFlow id="Flow_2" sourceRef="Task_Create_Account" targetRef="Task_Check_Credit"/>
    <bpmn:sequenceFlow id="Flow_3" sourceRef="Task_Check_Credit" targetRef="Task_Configure_Account"/>
    <bpmn:sequenceFlow id="Flow_4" sourceRef="Task_Configure_Account" targetRef="Task_Reserve_CTN"/>
    <bpmn:sequenceFlow id="Flow_5" sourceRef="Task_Reserve_CTN" targetRef="Task_Review_Credit_Policy"/>
    <bpmn:sequenceFlow id="Flow_6" sourceRef="Task_Review_Credit_Policy" targetRef="Task_Setup_Billing"/>
    <bpmn:sequenceFlow id="Flow_7" sourceRef="Task_Setup_Billing" targetRef="Task_Capture_TCP"/>
    <bpmn:sequenceFlow id="Flow_8" sourceRef="Task_Capture_TCP" targetRef="Task_Check_for_Fraud"/>
    <bpmn:sequenceFlow id="Flow_9" sourceRef="Task_Check_for_Fraud" targetRef="Task_Setup_Payment"/>
    <bpmn:sequenceFlow id="Flow_10" sourceRef="Task_Setup_Payment" targetRef="Task_Submit_Order"/>
    <bpmn:sequenceFlow id="Flow_11" sourceRef="Task_Submit_Order" targetRef="EndEvent_1"/>
    <bpmn:textAnnotation id="TextAnnotation_1">
      <bpmn:text>OPUS C, Digital IDP, FED US, INLAP, T Data, Avertack, TLG MOB, IDP Customer Graph Cloud</bpmn:text>
    </bpmn:textAnnotation>
    <bpmn:association id="Association_1" sourceRef="TextAnnotation_1" targetRef="Task_Create_Account"/>
    <bpmn:textAnnotation id="TextAnnotation_2">
      <bpmn:text>TLG MOB, OPUS C, CSI Parent Triage, CAS</bpmn:text>
    </bpmn:textAnnotation>
    <bpmn:association id="Association_2" sourceRef="TextAnnotation_2" targetRef="Task_Check_Credit"/>
    <bpmn:textAnnotation id="TextAnnotation_3">
      <bpmn:text>ORACLE SCM, UPM Prime Biller, OPUS C, TLG MOB, CPOP, CPC</bpmn:text>
    </bpmn:textAnnotation>
    <bpmn:association id="Association_3" sourceRef="TextAnnotation_3" targetRef="Task_Configure_Account"/>
    <bpmn:textAnnotation id="TextAnnotation_4">
      <bpmn:text>TLG MOB, NNA, OPUS C</bpmn:text>
    </bpmn:textAnnotation>
    <bpmn:association id="Association_4" sourceRef="TextAnnotation_4" targetRef="Task_Reserve_CTN"/>
    <bpmn:textAnnotation id="TextAnnotation_5">
      <bpmn:text>TLG MOB, CAS, CSI Customer Care, OPUS C</bpmn:text>
    </bpmn:textAnnotation>
    <bpmn:association id="Association_5" sourceRef="TextAnnotation_5" targetRef="Task_Review_Credit_Policy"/>
    <bpmn:textAnnotation id="TextAnnotation_6">
      <bpmn:text>OPUS C, TLG MOB, FED iCAS, CAS</bpmn:text>
    </bpmn:textAnnotation>
    <bpmn:association id="Association_6" sourceRef="TextAnnotation_6" targetRef="Task_Setup_Billing"/>
    <bpmn:textAnnotation id="TextAnnotation_7">
      <bpmn:text>TLG MOB, Optical, EDP, CSI Customer Care, OPUS C</bpmn:text>
    </bpmn:textAnnotation>
    <bpmn:association id="Association_7" sourceRef="TextAnnotation_7" targetRef="Task_Capture_TCP"/>
    <bpmn:textAnnotation id="TextAnnotation_8">
      <bpmn:text>Avertack, FED COMS, ORACLE SCM, CSI Customer Care, Digital IDP, OPUS C</bpmn:text>
    </bpmn:textAnnotation>
    <bpmn:association id="Association_8" sourceRef="TextAnnotation_8" targetRef="Task_Check_for_Fraud"/>
    <bpmn:textAnnotation id="TextAnnotation_9">
      <bpmn:text>CAPM, YODA, CSI CPSVC, OPUS C, CSI Customer Care, TLG MOB, UPM Prime Biller</bpmn:text>
    </bpmn:textAnnotation>
    <bpmn:association id="Association_9" sourceRef="TextAnnotation_9" targetRef="Task_Setup_Payment"/>
    <bpmn:textAnnotation id="TextAnnotation_10">
      <bpmn:text>Enabler C, TLG MOB, OPUS C, SC Switch Control TSC, YODA</bpmn:text>
    </bpmn:textAnnotation>
    <bpmn:association id="Association_10" sourceRef="TextAnnotation_10" targetRef="Task_Submit_Order"/>
  </bpmn:process>
  <bpmndi:BPMNDiagram id="BPMNDiagram_Process_Activate_New_Mobility_Customer" name="Line of Business: Mass Markets | Channel: Retail | Domain: Onboard  Activate | Subdomain: Setup  Activate | Product: Mobility | Business Flow: Activate New Mobility Customer">
    <bpmndi:BPMNPlane id="BPMNPlane_Process_Activate_New_Mobility_Customer" bpmnElement="Process_Activate_New_Mobility_Customer">
      <bpmndi:BPMNShape id="Lane_1_di" bpmnElement="Lane_1" isHorizontal="true" stroke="gray">
        <dc:Bounds x="70" y="80" width="2146" height="200"/>
      </bpmndi:BPMNShape>
      <bpmndi:BPMNShape id="StartEvent_1_di" bpmnElement="StartEvent_1" stroke="blue">
        <dc:Bounds x="150" y="162.0" width="36" height="36"/>
      </bpmndi:BPMNShape>
      <bpmndi:BPMNShape id="Task_Create_Account_di" bpmnElement="Task_Create_Account" stroke="blue">
        <dc:Bounds x="330" y="140.0" width="100" height="80"/>
      </bpmndi:BPMNShape>
      <bpmndi:BPMNShape id="Task_Check_Credit_di" bpmnElement="Task_Check_Credit" stroke="blue">
        <dc:Bounds x="510" y="140.0" width="100" height="80"/>
      </bpmndi:BPMNShape>
      <bpmndi:BPMNShape id="Task_Configure_Account_di" bpmnElement="Task_Configure_Account" stroke="blue">
        <dc:Bounds x="690" y="140.0" width="100" height="80"/>
      </bpmndi:BPMNShape>
      <bpmndi:BPMNShape id="Task_Reserve_CTN_di" bpmnElement="Task_Reserve_CTN" stroke="blue">
        <dc:Bounds x="870" y="140.0" width="100" height="80"/>
      </bpmndi:BPMNShape>
      <bpmndi:BPMNShape id="Task_Review_Credit_Policy_di" bpmnElement="Task_Review_Credit_Policy" stroke="blue">
        <dc:Bounds x="1050" y="140.0" width="100" height="80"/>
      </bpmndi:BPMNShape>
      <bpmndi:BPMNShape id="Task_Setup_Billing_di" bpmnElement="Task_Setup_Billing" stroke="blue">
        <dc:Bounds x="1230" y="140.0" width="100" height="80"/>
      </bpmndi:BPMNShape>
      <bpmndi:BPMNShape id="Task_Capture_TCP_di" bpmnElement="Task_Capture_TCP" stroke="blue">
        <dc:Bounds x="1410" y="140.0" width="100" height="80"/>
      </bpmndi:BPMNShape>
      <bpmndi:BPMNShape id="Task_Check_for_Fraud_di" bpmnElement="Task_Check_for_Fraud" stroke="blue">
        <dc:Bounds x="1590" y="140.0" width="100" height="80"/>
      </bpmndi:BPMNShape>
      <bpmndi:BPMNShape id="Task_Setup_Payment_di" bpmnElement="Task_Setup_Payment" stroke="blue">
        <dc:Bounds x="1770" y="140.0" width="100" height="80"/>
      </bpmndi:BPMNShape>
      <bpmndi:BPMNShape id="Task_Submit_Order_di" bpmnElement="Task_Submit_Order" stroke="blue">
        <dc:Bounds x="1950" y="140.0" width="100" height="80"/>
      </bpmndi:BPMNShape>
      <bpmndi:BPMNShape id="EndEvent_1_di" bpmnElement="EndEvent_1" stroke="blue">
        <dc:Bounds x="2130" y="162.0" width="36" height="36"/>
      </bpmndi:BPMNShape>
      <bpmndi:BPMNShape id="TextAnnotation_DiagramTitle_di" bpmnElement="TextAnnotation_DiagramTitle">
        <dc:Bounds x="658.0" y="5" width="1000" height="25"/>
      </bpmndi:BPMNShape>
      <bpmndi:BPMNShape id="TextAnnotation_LastUpdated_di" bpmnElement="TextAnnotation_LastUpdated">
        <dc:Bounds x="658.0" y="35" width="240" height="25"/>
      </bpmndi:BPMNShape>
      <bpmndi:BPMNShape id="TextAnnotation_1_di" bpmnElement="TextAnnotation_1">
        <dc:Bounds x="330" y="230.0" width="100" height="40"/>
        <bpmndi:BPMNLabel>
          <dc:Bounds x="330" y="230.0" width="100" height="40"/>
        </bpmndi:BPMNLabel>
      </bpmndi:BPMNShape>
      <bpmndi:BPMNShape id="TextAnnotation_2_di" bpmnElement="TextAnnotation_2">
        <dc:Bounds x="510" y="230.0" width="100" height="40"/>
        <bpmndi:BPMNLabel>
          <dc:Bounds x="510" y="230.0" width="100" height="40"/>
        </bpmndi:BPMNLabel>
      </bpmndi:BPMNShape>
      <bpmndi:BPMNShape id="TextAnnotation_3_di" bpmnElement="TextAnnotation_3">
        <dc:Bounds x="690" y="230.0" width="100" height="40"/>
        <bpmndi:BPMNLabel>
          <dc:Bounds x="690" y="230.0" width="100" height="40"/>
        </bpmndi:BPMNLabel>
      </bpmndi:BPMNShape>
      <bpmndi:BPMNShape id="TextAnnotation_4_di" bpmnElement="TextAnnotation_4">
        <dc:Bounds x="870" y="230.0" width="100" height="40"/>
        <bpmndi:BPMNLabel>
          <dc:Bounds x="870" y="230.0" width="100" height="40"/>
        </bpmndi:BPMNLabel>
      </bpmndi:BPMNShape>
      <bpmndi:BPMNShape id="TextAnnotation_5_di" bpmnElement="TextAnnotation_5">
        <dc:Bounds x="1050" y="230.0" width="100" height="40"/>
        <bpmndi:BPMNLabel>
          <dc:Bounds x="1050" y="230.0" width="100" height="40"/>
        </bpmndi:BPMNLabel>
      </bpmndi:BPMNShape>
      <bpmndi:BPMNShape id="TextAnnotation_6_di" bpmnElement="TextAnnotation_6">
        <dc:Bounds x="1230" y="230.0" width="100" height="40"/>
        <bpmndi:BPMNLabel>
          <dc:Bounds x="1230" y="230.0" width="100" height="40"/>
        </bpmndi:BPMNLabel>
      </bpmndi:BPMNShape>
      <bpmndi:BPMNShape id="TextAnnotation_7_di" bpmnElement="TextAnnotation_7">
        <dc:Bounds x="1410" y="230.0" width="100" height="40"/>
        <bpmndi:BPMNLabel>
          <dc:Bounds x="1410" y="230.0" width="100" height="40"/>
        </bpmndi:BPMNLabel>
      </bpmndi:BPMNShape>
      <bpmndi:BPMNShape id="TextAnnotation_8_di" bpmnElement="TextAnnotation_8">
        <dc:Bounds x="1590" y="230.0" width="100" height="40"/>
        <bpmndi:BPMNLabel>
          <dc:Bounds x="1590" y="230.0" width="100" height="40"/>
        </bpmndi:BPMNLabel>
      </bpmndi:BPMNShape>
      <bpmndi:BPMNShape id="TextAnnotation_9_di" bpmnElement="TextAnnotation_9">
        <dc:Bounds x="1770" y="230.0" width="100" height="40"/>
        <bpmndi:BPMNLabel>
          <dc:Bounds x="1770" y="230.0" width="100" height="40"/>
        </bpmndi:BPMNLabel>
      </bpmndi:BPMNShape>
      <bpmndi:BPMNShape id="TextAnnotation_10_di" bpmnElement="TextAnnotation_10">
        <dc:Bounds x="1950" y="230.0" width="100" height="40"/>
        <bpmndi:BPMNLabel>
          <dc:Bounds x="1950" y="230.0" width="100" height="40"/>
        </bpmndi:BPMNLabel>
      </bpmndi:BPMNShape>
      <bpmndi:BPMNEdge id="Association_1_di" bpmnElement="Association_1">
        <di:waypoint x="380.0" y="230.0"/>
        <di:waypoint x="380.0" y="220.0"/>
      </bpmndi:BPMNEdge>
      <bpmndi:BPMNEdge id="Association_2_di" bpmnElement="Association_2">
        <di:waypoint x="560.0" y="230.0"/>
        <di:waypoint x="560.0" y="220.0"/>
      </bpmndi:BPMNEdge>
      <bpmndi:BPMNEdge id="Association_3_di" bpmnElement="Association_3">
        <di:waypoint x="740.0" y="230.0"/>
        <di:waypoint x="740.0" y="220.0"/>
      </bpmndi:BPMNEdge>
      <bpmndi:BPMNEdge id="Association_4_di" bpmnElement="Association_4">
        <di:waypoint x="920.0" y="230.0"/>
        <di:waypoint x="920.0" y="220.0"/>
      </bpmndi:BPMNEdge>
      <bpmndi:BPMNEdge id="Association_5_di" bpmnElement="Association_5">
        <di:waypoint x="1100.0" y="230.0"/>
        <di:waypoint x="1100.0" y="220.0"/>
      </bpmndi:BPMNEdge>
      <bpmndi:BPMNEdge id="Association_6_di" bpmnElement="Association_6">
        <di:waypoint x="1280.0" y="230.0"/>
        <di:waypoint x="1280.0" y="220.0"/>
      </bpmndi:BPMNEdge>
      <bpmndi:BPMNEdge id="Association_7_di" bpmnElement="Association_7">
        <di:waypoint x="1460.0" y="230.0"/>
        <di:waypoint x="1460.0" y="220.0"/>
      </bpmndi:BPMNEdge>
      <bpmndi:BPMNEdge id="Association_8_di" bpmnElement="Association_8">
        <di:waypoint x="1640.0" y="230.0"/>
        <di:waypoint x="1640.0" y="220.0"/>
      </bpmndi:BPMNEdge>
      <bpmndi:BPMNEdge id="Association_9_di" bpmnElement="Association_9">
        <di:waypoint x="1820.0" y="230.0"/>
        <di:waypoint x="1820.0" y="220.0"/>
      </bpmndi:BPMNEdge>
      <bpmndi:BPMNEdge id="Association_10_di" bpmnElement="Association_10">
        <di:waypoint x="2000.0" y="230.0"/>
        <di:waypoint x="2000.0" y="220.0"/>
      </bpmndi:BPMNEdge>
      <bpmndi:BPMNEdge id="Flow_1_di" bpmnElement="Flow_1" stroke="blue">
        <di:waypoint x="186" y="180.0"/>
        <di:waypoint x="330" y="180.0"/>
      </bpmndi:BPMNEdge>
      <bpmndi:BPMNEdge id="Flow_2_di" bpmnElement="Flow_2" stroke="blue">
        <di:waypoint x="430" y="180.0"/>
        <di:waypoint x="510" y="180.0"/>
      </bpmndi:BPMNEdge>
      <bpmndi:BPMNEdge id="Flow_3_di" bpmnElement="Flow_3" stroke="blue">
        <di:waypoint x="610" y="180.0"/>
        <di:waypoint x="690" y="180.0"/>
      </bpmndi:BPMNEdge>
      <bpmndi:BPMNEdge id="Flow_4_di" bpmnElement="Flow_4" stroke="blue">
        <di:waypoint x="790" y="180.0"/>
        <di:waypoint x="870" y="180.0"/>
      </bpmndi:BPMNEdge>
      <bpmndi:BPMNEdge id="Flow_5_di" bpmnElement="Flow_5" stroke="blue">
        <di:waypoint x="970" y="180.0"/>
        <di:waypoint x="1050" y="180.0"/>
      </bpmndi:BPMNEdge>
      <bpmndi:BPMNEdge id="Flow_6_di" bpmnElement="Flow_6" stroke="blue">
        <di:waypoint x="1150" y="180.0"/>
        <di:waypoint x="1230" y="180.0"/>
      </bpmndi:BPMNEdge>
      <bpmndi:BPMNEdge id="Flow_7_di" bpmnElement="Flow_7" stroke="blue">
        <di:waypoint x="1330" y="180.0"/>
        <di:waypoint x="1410" y="180.0"/>
      </bpmndi:BPMNEdge>
      <bpmndi:BPMNEdge id="Flow_8_di" bpmnElement="Flow_8" stroke="blue">
        <di:waypoint x="1510" y="180.0"/>
        <di:waypoint x="1590" y="180.0"/>
      </bpmndi:BPMNEdge>
      <bpmndi:BPMNEdge id="Flow_9_di" bpmnElement="Flow_9" stroke="blue">
        <di:waypoint x="1690" y="180.0"/>
        <di:waypoint x="1770" y="180.0"/>
      </bpmndi:BPMNEdge>
      <bpmndi:BPMNEdge id="Flow_10_di" bpmnElement="Flow_10" stroke="blue">
        <di:waypoint x="1870" y="180.0"/>
        <di:waypoint x="1950" y="180.0"/>
      </bpmndi:BPMNEdge>
      <bpmndi:BPMNEdge id="Flow_11_di" bpmnElement="Flow_11" stroke="blue">
        <di:waypoint x="2050" y="180.0"/>
        <di:waypoint x="2130" y="180.0"/>
      </bpmndi:BPMNEdge>
    </bpmndi:BPMNPlane>
  </bpmndi:BPMNDiagram>
</bpmn:definitions>